extended_fastapi/__init__.py
extended_fastapi/app.py
extended_fastapi/backend_config.py
extended_fastapi/config.py
extended_fastapi-0.1.0.dist-info/METADATA
extended_fastapi-0.1.0.dist-info/WHEEL
extended_fastapi-0.1.0.dist-info/RECORD
