Metadata-Version: 2.1
Name: extended-fastapi
Version: 0.1.0
Summary: FastAPI utilities.
License: MIT
Author: Paweł Pozorski
Author-email: pawel.pozorski@medwave.app
Requires-Python: >=3.12,<4.0
Classifier: License :: OSI Approved :: MIT License
Classifier: Programming Language :: Python :: 3
Classifier: Programming Language :: Python :: 3.12
Requires-Dist: extended-logging (>=0.1.0,<0.2.0)
Requires-Dist: extended-sql (>=0.1.0,<0.2.0)
Requires-Dist: fastapi (>=0.111.0,<0.112.0)
Requires-Dist: pydantic (>=2.7.2,<3.0.0)
Requires-Dist: pydantic-core (>=2.18.3,<3.0.0)
Requires-Dist: pydantic-settings (>=2.2.1,<3.0.0)
